alice_api/__init__.py
alice_api/main.py
alice_api-1.0.1.dist-info/LICENSE
alice_api-1.0.1.dist-info/METADATA
alice_api-1.0.1.dist-info/WHEEL
alice_api-1.0.1.dist-info/top_level.txt
alice_api-1.0.1.dist-info/RECORD
