Metadata-Version: 2.1
Name: alice-api
Version: 1.0.1
Summary: Alice api its come with sms spammer, truewallet system and host system!
Home-page: https://github.com/alice-api/alice-api
Author: pipatpong
Author-email: kanyatit2500@gmail.com
License: MIT
Classifier: Programming Language :: Python :: 3
Classifier: Development Status :: 4 - Beta
Classifier: License :: OSI Approved :: MIT License
Classifier: Operating System :: OS Independent
License-File: LICENSE
Requires-Dist: flask
Requires-Dist: requests
Requires-Dist: datetime
